PyWebWrench/__init__.py
PyWebWrench/py_web_wrench.py
PyWebWrench-0.0.7.dist-info/METADATA
PyWebWrench-0.0.7.dist-info/WHEEL
PyWebWrench-0.0.7.dist-info/top_level.txt
PyWebWrench-0.0.7.dist-info/RECORD
