Metadata-Version: 2.1
Name: PyWebWrench
Version: 0.0.7
Summary: PyWebWrench is a Python library that enables you to view web pages and make HTTP requests
Home-page: UNKNOWN
Author: 09u2h4n
Author-email: 09u2h4n.y1lm42@gmail.com
License: UNKNOWN
Project-URL: Source Code, https://github.com/09u2h4n/PyWebWrench
Project-URL: Author's Github, https://github.com/09u2h4n
Platform: UNKNOWN
Requires-Dist: playwright
Requires-Dist: requests
